st_react_flow_pro/__init__.py
st_react_flow_pro/frontend/dist/index.html
st_react_flow_pro/frontend/dist/vite.svg
st_react_flow_pro/frontend/dist/assets/index-DU14Q3SR.js
st_react_flow_pro/frontend/dist/assets/index-vbh5Iq1y.css
st_react_flow_pro-0.1.3.dist-info/LICENSE
st_react_flow_pro-0.1.3.dist-info/METADATA
st_react_flow_pro-0.1.3.dist-info/WHEEL
st_react_flow_pro-0.1.3.dist-info/top_level.txt
st_react_flow_pro-0.1.3.dist-info/RECORD
