Metadata-Version: 2.2
Name: st-react-flow-pro
Version: 0.1.3
Summary: Streamlit component that allows you to do X
Author: Muhammad Ahmad
Author-email: muhammad.ahmad@redbuffer.net
Requires-Python: >=3.7
License-File: LICENSE
Requires-Dist: streamlit>=1.2
Requires-Dist: jinja2
Dynamic: author
Dynamic: author-email
Dynamic: description
Dynamic: description-content-type
Dynamic: requires-dist
Dynamic: requires-python
Dynamic: summary
